lumimqtt/__init__.py
lumimqtt/__main__.py
lumimqtt/__version__.py
lumimqtt/button.py
lumimqtt/commands.py
lumimqtt/device.py
lumimqtt/light.py
lumimqtt/lumimqtt.py
lumimqtt/platform.py
lumimqtt/sensors.py
lumimqtt-1.0.18.dist-info/LICENSE
lumimqtt-1.0.18.dist-info/METADATA
lumimqtt-1.0.18.dist-info/WHEEL
lumimqtt-1.0.18.dist-info/entry_points.txt
lumimqtt-1.0.18.dist-info/top_level.txt
lumimqtt-1.0.18.dist-info/RECORD
