Metadata-Version: 2.2
Name: lumimqtt
Version: 1.0.18
Summary: Xiaomi Lumi Gateway MQTT integration
Home-page: https://github.com/openlumi/lumimqtt/
Author: Ivan Belokobylskiy
Author-email: belokobylskij@gmail.com
Classifier: Programming Language :: Python :: 3.7
Classifier: Programming Language :: Python :: 3.8
Classifier: Programming Language :: Python :: 3.9
Classifier: Programming Language :: Python :: 3.10
Classifier: Programming Language :: Python :: 3.11
Classifier: Programming Language :: Python :: 3 :: Only
Classifier: Topic :: Utilities
License-File: LICENSE
Requires-Dist: evdev>=1.0.0
Requires-Dist: aio-mqtt-mod>=0.3.2
Dynamic: author
Dynamic: author-email
Dynamic: classifier
Dynamic: description
Dynamic: description-content-type
Dynamic: home-page
Dynamic: requires-dist
Dynamic: summary
